LICENSE
MANIFEST.in
README.md
setup.py
rwpt/__init__.py
rwpt/ro_decoder.py
rwpt/ro_normalizer.py
rwpt/ro_pretokenizer.py
rwpt/ro_wordpiece.py
rwpt.egg-info/PKG-INFO
rwpt.egg-info/SOURCES.txt
rwpt.egg-info/dependency_links.txt
rwpt.egg-info/requires.txt
rwpt.egg-info/top_level.txt
rwpt/model/vocab.txt
rwpt/rodna/README.md
rwpt/rodna/tokenizer.py
rwpt/rodna/data/abbrs.txt
rwpt/rodna/data/mwes.txt
rwpt/rodna/data/wordforms.txt