Metadata-Version: 2.1
Name: rwpt
Version: 1.0.2
Summary: A Romanian WordPiece tokenizer
Home-page: https://github.com/racai-ai/ro-wordpiece-tokenizer
Author: Radu Ion
Author-email: radu@racai.ro
License: MIT License
Classifier: Development Status :: 5 - Production/Stable
Classifier: Intended Audience :: Science/Research
Classifier: Intended Audience :: Developers
Classifier: License :: OSI Approved :: MIT License
Classifier: Operating System :: POSIX :: Linux
Classifier: Operating System :: Microsoft :: Windows :: Windows 10
Classifier: Operating System :: Microsoft :: Windows :: Windows 11
Classifier: Natural Language :: Romanian
Classifier: Programming Language :: Python :: 3.10
Classifier: Programming Language :: Python :: 3.11
Classifier: Topic :: Scientific/Engineering :: Artificial Intelligence
Classifier: Topic :: Text Processing :: Linguistic
License-File: LICENSE
